DAICommit/__main__.py
DAICommit/commands/__init__.py
DAICommit/commands/commit.py
DAICommit/commands/config.py
DAICommit/engine/Engine.py
DAICommit/engine/anthropic.py
DAICommit/engine/gemini.py
DAICommit/engine/openAi.py
DAICommit/i18n/__init__.py
DAICommit/i18n/cs.py
DAICommit/i18n/de.py
DAICommit/i18n/en.py
DAICommit/i18n/es_ES.py
DAICommit/i18n/fr.py
DAICommit/i18n/id_ID.py
DAICommit/i18n/it.py
DAICommit/i18n/ja.py
DAICommit/i18n/ko.py
DAICommit/i18n/nl.py
DAICommit/i18n/pl.py
DAICommit/i18n/pt_br.py
DAICommit/i18n/ru.py
DAICommit/i18n/sv.py
DAICommit/i18n/th.py
DAICommit/i18n/tr.py
DAICommit/i18n/vi_VN.py
DAICommit/i18n/zh_CN.py
DAICommit/i18n/zh_TW.py
DAICommit/utills/__init__.py
DAICommit/utills/cli.py
DAICommit/utills/config.py
DAICommit/utills/engine.py
DAICommit/utills/generateCommitMessageFromGitDiff.py
DAICommit/utills/git.py
DAICommit/utills/mergeDiffs.py
DAICommit/utills/prompts.py
DAICommit/utills/removeConventionalCommitWord.py
DAICommit/utills/tokenCount.py
DAICommit/utills/trytm.py
DAICommit-1.0.2.dist-info/LICENSE
DAICommit-1.0.2.dist-info/METADATA
DAICommit-1.0.2.dist-info/WHEEL
DAICommit-1.0.2.dist-info/entry_points.txt
DAICommit-1.0.2.dist-info/top_level.txt
DAICommit-1.0.2.dist-info/RECORD
