Metadata-Version: 2.1
Name: DAICommit
Version: 1.0.2
Summary: Auto-generate impressive commits in 1 second. Killing lame commits with AI 🤯🔫
Home-page: https://github.com/Matvey-Guzienko/daicommit
Author: Discq192
Author-email: guziienkomatvei@gmail.com
License: MIT License
Keywords: AI commit git aicommit
Classifier: Programming Language :: Python :: 3.10
Classifier: License :: OSI Approved :: MIT License
Classifier: Operating System :: OS Independent
Requires-Python: >=3.10
License-File: LICENSE
Requires-Dist: openai>=1.53.0
Requires-Dist: google-generativeai>=0.8.3
Requires-Dist: anthropic>=0.38.0
Requires-Dist: rich==13.9.4
Requires-Dist: pick==2.4.0
Requires-Dist: GitPython>=3.1.43
Requires-Dist: colorama>=0.4.6
Requires-Dist: pydantic>=2.9.2
Requires-Dist: tiktoken>=0.8.0
